benfords_law/__init__.py
benfords_law/benfords_law.py
benfords_law-1.0.0.dist-info/LICENSE
benfords_law-1.0.0.dist-info/METADATA
benfords_law-1.0.0.dist-info/WHEEL
benfords_law-1.0.0.dist-info/top_level.txt
benfords_law-1.0.0.dist-info/RECORD
