Metadata-Version: 2.1
Name: benfords-law
Version: 1.0.0
Summary: Apply and run tests of Newcomb-Benford's Law on provided data
Home-page: https://github.com/mawuliadjei/benfords_law
Author: Mawuli Adjei
Author-email: mawuliadjei@gmail.com
License: MIT
Project-URL: Documentation, https://benfords-law.readthedocs.io/
Project-URL: Source, https://github.com/mawuliadjei/benfords_law/
Project-URL: Tracker, https://github.com/mawuliadjei/benfords_law/issues
Keywords: Newcomb Benford Analogous-Numbers Statistics Testing Law Benfordness Test
Platform: UNKNOWN
Classifier: Development Status :: 5 - Production/Stable
Classifier: Intended Audience :: Developers
Classifier: Topic :: Software Development :: Build Tools
Classifier: License :: OSI Approved :: MIT License
Classifier: Programming Language :: Python :: 3
Classifier: Programming Language :: Python :: 3.7
Requires-Python: >=3.6
Requires-Dist: numpy (==1.17.1)
Requires-Dist: pandas (==0.25.1)
Requires-Dist: scipy (>=1.5.4)
Requires-Dist: matplotlib (==3.3.3)
